<?xml version="1.0" encoding="utf-8"?>
<openerp>
	<data>							

		<menuitem 	
					id="menu_account_accountingHideHeader"
					parent="base.menu_administration"
					name="Unused Accounting Menu"
		/>
		
		<menuitem 
				action="account_voucher.action_voucher_list" 
				id="account_voucher.menu_encode_entries_by_voucher" 
				parent="menu_account_accountingHideHeader" />
				
        <menuitem 
        		action="account_voucher.action_vendor_payment" 
        		icon="STOCK_JUSTIFY_FILL"
            	id="account_voucher.menu_action_vendor_payment"  
            	parent="menu_account_accountingHideHeader"/>	
            	
        <menuitem 
        		action="account_voucher.action_vendor_receipt" 
        		icon="STOCK_JUSTIFY_FILL"
            	id="account_voucher.menu_action_vendor_receipt"  
            	parent="menu_account_accountingHideHeader"/>     
            	
        <menuitem 
        		id="account_voucher.menu_action_sale_receipt" 
        		icon="STOCK_JUSTIFY_FILL"
            	action="account_voucher.action_sale_receipt"
            	parent="menu_account_accountingHideHeader"
            	groups="base.group_extended"/>          
            	
        <menuitem 
        		id="account_voucher.menu_action_purchase_receipt" 
        		icon="STOCK_JUSTIFY_FILL"
            	action="account_voucher.action_purchase_receipt" 
            	parent="menu_account_accountingHideHeader"
            	groups="base.group_extended"/>      
            	
        <menuitem 
			id="account.menu_eaction_account_moves_sale"        
        	action="account.action_account_moves_sale" 
        	sequence="16" 
			parent="menu_account_accountingHideHeader"
            icon="STOCK_JUSTIFY_FILL" 
            groups="account.group_account_user,account.group_account_manager"/>  
            
        <menuitem 
        	action="account.action_account_moves_purchase"
            id="account.menu_eaction_account_moves_purchase"
			parent="menu_account_accountingHideHeader"
            icon="STOCK_JUSTIFY_FILL"
            sequence="16"
            groups="account.group_account_user,account.group_account_manager"/>    	  	  
            
        <menuitem
            action="account.action_account_moves_bank"
            icon="STOCK_JUSTIFY_FILL"
            id="account.menu_action_account_moves_bank"
			parent="menu_account_accountingHideHeader"
            sequence="16"
            groups="account.group_account_user,account.group_account_manager"
        />     			
        
        <menuitem 
        	string="Bank Statements" 
        	action="account.action_bank_statement_tree" 
        	id="account.menu_bank_statement_tree" 
			parent="menu_account_accountingHideHeader"
        	sequence="7"/>	
        	
        <menuitem 
        	action="account.action_view_bank_statement_tree" 
        	id="account.journal_cash_move_lines"
			parent="menu_account_accountingHideHeader" />
																																																		
																																																
	</data>
</openerp>
